[
  {
    "full_name": "grpc/grpc-go",
    "stargazers_count": 19263,
    "open_issues_count": 136,
    "forks_count": 4209
  },
  {
    "full_name": "ktr0731/evans",
    "stargazers_count": 3978,
    "open_issues_count": 29,
    "forks_count": 184
  },
  {
    "full_name": "rerost/giro",
    "stargazers_count": 16,
    "open_issues_count": 0,
    "forks_count": 0
  },
  {
    "full_name": "open-sauced/open-sauced",
    "stargazers_count": 900,
    "open_issues_count": 0,
    "forks_count": 815
  }
]